[{
 "type":
 "schnitzler-tagebuch",
 "color":
 "#037a33",
 "filename":
 "entry__1891-02-23",
 "caption":
 "Tagebuch",
 "idno":
 "https://schnitzler-tagebuch.acdh.oeaw.ac.at/entry__1891-02-23.html",
 "head":
 "Tagebucheintrag zum 23. Februar 1891",
 "desc":
{"listPerson":
  [
{
 "persName":
 "Gustav Frieberger",
 "ref":
 "pmb3452"},
 {
 "persName":
 "Jaques Joachim",
 "ref":
 "pmb18870"},
 {
 "persName":
 "Rudolf Lothar",
 "ref":
 "pmb2570"},
 {
 "persName":
 "Emil Reich",
 "ref":
 "pmb9449"},
 {
 "persName":
 "Schwarz",
 "ref":
 "pmb24589"},
 {
 "persName":
 "Adolf Weizmann",
 "ref":
 "pmb26899"},
 {
 "persName":
 "Alexander Engel",
 "ref":
 "pmb11253"},
 {
 "persName":
 "Eduard Michael Kafka",
 "ref":
 "pmb2563"}]
}
}, {
 "type":
 "schnitzler-cmif",
 "subtype":
 "#d2b0f559-bde7-4114-82b9-741a8810c463",
 "color":
 "#654321",
 "caption":
 "Gedruckte Briefwechsel",
 "head":
 "Olga Waissnix an Arthur Schnitzler, 23.2.1891?",
 "source":
 "Arthur Schnitzler und Waissnix, Olga: Liebe, die starb vor der Zeit. Ein Briefwechsel. Mit einem Vorwort von Hans Weigel. Mit 16 Seiten Kunstdruckbildern. Hg. v. Therese Nickl und Heinrich Schnitzler. Wien, München, Zürich: Verlag Fritz Molden 1970. (PDF: https://schnitzler-briefe.acdh.oeaw.ac.at)"
}] 