[{
 "type":
 "schnitzler-tagebuch",
 "color":
 "#037a33",
 "filename":
 "entry__1896-04-08",
 "caption":
 "Tagebuch",
 "idno":
 "https://schnitzler-tagebuch.acdh.oeaw.ac.at/entry__1896-04-08.html",
 "head":
 "Tagebucheintrag zum 8. April 1896",
 "desc":
{"listPerson":
  [
{
 "persName":
 "Babette",
 "ref":
 "pmb13623"},
 {
 "persName":
 "Max Eugen Burckhard",
 "ref":
 "pmb11036"},
 {
 "persName":
 "Dora Fournier",
 "ref":
 "pmb16420"},
 {
 "persName":
 "Wilhelm Korvin",
 "ref":
 "pmb19637"},
 {
 "persName":
 "Louise Schnitzler",
 "ref":
 "pmb12701"},
 {
 "persName":
 "Siegfried J. Rappa",
 "ref":
 "pmb23057"},
 {
 "persName":
 "Marie Reinhard",
 "ref":
 "pmb2378"}],
 "listBibl":
  [
 {
 "title":
 "Götz von Berlichingen mit der eisernen Hand",
 "ref":
 "pmb31071"}
 ,  {
 "title":
 "Dom Karlos, Infant von Spanien",
 "ref":
 "pmb33023"}
 ],
 "listPlace":
  [
 {
 "placeName":
 "Burgtheater",
 "ref":
 "pmb14"}
 ,  {
 "placeName":
 "VI., Mariahilf",
 "ref":
 "pmb56"}
 ,  {
 "placeName":
 "Argentinierstraße",
 "ref":
 "pmb92138"}
 ]
}
}, {
 "type":
 "schnitzler-briefe",
 "color":
 "#A63437",
 "filename":
 "L03866",
 "caption":
 "Briefe mit Autorinnen und Autoren",
 "idno":
 "https://schnitzler-briefe.acdh.oeaw.ac.at/L03866.html",
 "head":
 "Theodor Herzl an Arthur Schnitzler, 8. 4. 1896",
 "desc":
{"listPerson":
  [
{
 "persName":
 "Theodor Herzl",
 "ref":
 "pmb11673"},
 {
 "persName":
 "Arthur Schnitzler",
 "ref":
 "pmb2121"}],
 "listPlace":
  [
 {
 "placeName":
 "Fichtegasse 11",
 "ref":
 "pmb237534"}
 ,  {
 "placeName":
 "Wien",
 "ref":
 "pmb50"}
 ],
 "listOrg":
  [
 {
 "orgName":
 "Neue Freie Presse",
 "ref":
 "pmb29351"}
 ]
}
}] 