[{
 "type":
 "schnitzler-tagebuch",
 "color":
 "#037a33",
 "filename":
 "entry__1897-02-02",
 "caption":
 "Tagebuch",
 "idno":
 "https://schnitzler-tagebuch.acdh.oeaw.ac.at/entry__1897-02-02.html",
 "head":
 "Tagebucheintrag zum 2. Februar 1897",
 "desc":
{"listPerson":
  [
{
 "persName":
 "Richard Beer-Hofmann",
 "ref":
 "pmb10863"},
 {
 "persName":
 "August Wärndorfer",
 "ref":
 "pmb27380"},
 {
 "persName":
 "Marie Reinhard",
 "ref":
 "pmb2378"},
 {
 "persName":
 "Adrienne Wärndorfer",
 "ref":
 "pmb27377"},
 {
 "persName":
 "Paula Beer-Hofmann",
 "ref":
 "pmb10860"}]
}
}] 