[{
 "type":
 "schnitzler-tagebuch",
 "color":
 "#037a33",
 "filename":
 "entry__1900-10-26",
 "caption":
 "Tagebuch",
 "idno":
 "https://schnitzler-tagebuch.acdh.oeaw.ac.at/entry__1900-10-26.html",
 "head":
 "Tagebucheintrag zum 26. Oktober 1900",
 "desc":
{"listPerson":
  [
{
 "persName":
 "Leopoldine Kirchrath",
 "ref":
 "pmb19337"},
 {
 "persName":
 "Albert Speyer",
 "ref":
 "pmb25179"},
 {
 "persName":
 "Hermann Speyer",
 "ref":
 "pmb25184"},
 {
 "persName":
 "Clara Speyer",
 "ref":
 "pmb25182"},
 {
 "persName":
 "Olga Schnitzler",
 "ref":
 "pmb2173"}]
}
}, {
 "type":
 "wienerschnitzler",
 "color":
 "#6F5106",
 "caption":
 "Wiener Schnitzler",
 "idno":
 "https://wienerschnitzler.org/tag.html#1900-10-26",
 "head":
 "Wien",
 "desc":
{"listPlace":
  [
 {
 "placeName":
 "I., Innere Stadt",
 "ref":
 ""}
 ,  {
 "placeName":
 "II., Leopoldstadt",
 "ref":
 ""}
 ,  {
 "placeName":
 "IX., Alsergrund",
 "ref":
 ""}
 ]
}
}] 