[{
 "type":
 "schnitzler-tagebuch",
 "color":
 "#037a33",
 "filename":
 "entry__1901-01-28",
 "caption":
 "Tagebuch",
 "idno":
 "https://schnitzler-tagebuch.acdh.oeaw.ac.at/entry__1901-01-28.html",
 "head":
 "Tagebuch, 28. Januar 1901",
 "desc":
{"listPerson":
  [
{
 "persName":
 "Leopoldine Müller",
 "ref":
 "person_18303"},
 {
 "persName":
 "Aur. St.",
 "ref":
 "person_20305"},
 {
 "persName":
 "Olga Schnitzler",
 "ref":
 "person_19832"}]
}
}, {
 "type":
 "schnitzler-briefe",
 "color":
 "#A63437",
 "filename":
 "L04237",
 "caption":
 "Briefe mit Autorinnen und Autoren",
 "idno":
 "https://schnitzler-briefe.acdh.oeaw.ac.at/L04237.html",
 "head":
 "Arthur Schnitzler an Theodor von Sosnosky, [zwischen 26. 1. 1901 und
                  29. 1. 1901?]",
 "desc":
{"listPerson":
  [
{
 "persName":
 "Arthur Schnitzler",
 "ref":
 "pmb2121"},
 {
 "persName":
 "Theodor von Sosnosky",
 "ref":
 "pmb9941"},
 {
 "persName":
 "Theodor von Sosnosky",
 "ref":
 "pmb9941"}],
 "listBibl":
  [
 {
 "title":
 "Reigen. Zehn Dialoge",
 "ref":
 "pmb29855"}
 ,  {
 "title":
 "»Jung-Wien«. Studienblätter",
 "ref":
 "pmb334964"}
 ,  {
 "title":
 "Norddeutsche Allgemeine Zeitung",
 "ref":
 "pmb334898"}
 ,  {
 "title":
 "Neues Wiener Tagblatt",
 "ref":
 "pmb41321"}
 ],
 "listPlace":
  [
 {
 "placeName":
 "Wien",
 "ref":
 "pmb50"}
 ,  {
 "placeName":
 "Kremsmünster",
 "ref":
 "pmb48393"}
 ]
}
}, {
 "type":
 "wienerschnitzler",
 "color":
 "#6F5106",
 "caption":
 "Wiener Schnitzler",
 "idno":
 "https://wienerschnitzler.org/tag.html#1901-01-28",
 "head":
 "Wien",
 "desc":
{"listPlace":
  [
 {
 "placeName":
 "II., Leopoldstadt",
 "ref":
 ""}
 ,  {
 "placeName":
 "IX., Alsergrund",
 "ref":
 ""}
 ]
}
}] 