[{
 "type":
 "schnitzler-tagebuch",
 "color":
 "#037a33",
 "filename":
 "entry__1903-02-03",
 "caption":
 "Tagebuch",
 "idno":
 "https://schnitzler-tagebuch.acdh.oeaw.ac.at/entry__1903-02-03.html",
 "head":
 "Tagebucheintrag zum 3. Februar 1903",
 "desc":
{"listPerson":
  [
{
 "persName":
 "Anton Bettelheim",
 "ref":
 "pmb10912"}]
}
}, {
 "type":
 "URL",
 "subtype":
 "schnitzler-kultur",
 "filename":
 "pmb209279",
 "idno":
 "https://schnitzler-kultur.acdh.oeaw.ac.at/pmb209279.html",
 "head":
 "Symphoniekonzert, 3.2.1903",
 "desc":
{"listOrg":
  [
 {
 "orgName":
 "Wiener Symphoniker",
 "ref":
 ""}
 ],
 "listPerson":
  [
{
 "persName":
 "Arthur Schnitzler",
 "ref":
 ""},
 {
 "persName":
 "Ferdinand Löwe",
 "ref":
 ""}],
 "listPlace":
  [
 {
 "placeName":
 "Musikverein",
 "ref":
 ""}
 ]
}
}] 