[{
 "type":
 "schnitzler-tagebuch",
 "color":
 "#037a33",
 "filename":
 "entry__1903-12-27",
 "caption":
 "Tagebuch",
 "idno":
 "https://schnitzler-tagebuch.acdh.oeaw.ac.at/entry__1903-12-27.html",
 "head":
 "Tagebucheintrag zum 27. Dezember 1903",
 "desc":
{"listPerson":
  [
{
 "persName":
 "Richard Beer-Hofmann",
 "ref":
 "pmb10863"},
 {
 "persName":
 "Ludwig van Beethoven",
 "ref":
 "pmb10866"},
 {
 "persName":
 "Emma Bloch",
 "ref":
 "pmb14298"},
 {
 "persName":
 "Gertrude von Hofmannsthal",
 "ref":
 "pmb2292"},
 {
 "persName":
 "Wolfgang Amadeus Mozart",
 "ref":
 "pmb12303"},
 {
 "persName":
 "Louise Schnitzler",
 "ref":
 "pmb12701"},
 {
 "persName":
 "Leo Van-Jung",
 "ref":
 "pmb26392"},
 {
 "persName":
 "Paula Beer-Hofmann",
 "ref":
 "pmb10860"},
 {
 "persName":
 "Hugo von Hofmannsthal",
 "ref":
 "pmb11740"},
 {
 "persName":
 "Raoul Markbreiter",
 "ref":
 "pmb21050"},
 {
 "persName":
 "Franziska Mütter",
 "ref":
 "pmb21766"},
 {
 "persName":
 "Josefine Rothenstein",
 "ref":
 "pmb23661"}],
 "listBibl":
  [
 {
 "title":
 "Der einsame Weg. Schauspiel in fünf Akten",
 "ref":
 "pmb29985"}
 ,  {
 "title":
 "Streichquartett Nr. 3 D-Dur op. 18,3",
 "ref":
 "pmb77179"}
 ,  {
 "title":
 "Symphonie Nr. 40 g-Moll KV 550",
 "ref":
 "pmb77225"}
 ]
}
}] 