[{
 "type":
 "schnitzler-tagebuch",
 "color":
 "#037a33",
 "filename":
 "entry__1903-05-04",
 "caption":
 "Tagebuch",
 "idno":
 "https://schnitzler-tagebuch.acdh.oeaw.ac.at/entry__1903-05-04.html",
 "head":
 "Tagebuch, 4. Mai 1903",
 "desc":
{"listPerson":
  [
{
 "persName":
 "Moriz Károlyi",
 "ref":
 "person_16735"}],
 "listPlace":
  [
 {
 "placeName":
 "XIII., Hietzing",
 "ref":
 "pmb63"}
 ]
}
}, {
 "type":
 "schnitzler-briefe",
 "color":
 "#A63437",
 "filename":
 "L04205",
 "caption":
 "Briefe mit Autorinnen und Autoren",
 "idno":
 "https://schnitzler-briefe.acdh.oeaw.ac.at/L04205.html",
 "head":
 "Arthur Schnitzler an Gustav Schwarzkopf, [4. 5. 1903?]",
 "desc":
{"listPerson":
  [
{
 "persName":
 "Arthur Schnitzler",
 "ref":
 "pmb2121"},
 {
 "persName":
 "Gustav Schwarzkopf",
 "ref":
 "pmb12740"},
 {
 "persName":
 "Gustav Schwarzkopf",
 "ref":
 "pmb12740"},
 {
 "persName":
 "Olga Schnitzler",
 "ref":
 "pmb2173"},
 {
 "persName":
 "Paul Marx",
 "ref":
 "pmb21647"},
 {
 "persName":
 "Paul Goldmann",
 "ref":
 "pmb11485"}],
 "listPlace":
  [
 {
 "placeName":
 "Wien",
 "ref":
 "pmb50"}
 ,  {
 "placeName":
 "Gentzgasse 110",
 "ref":
 "pmb232166"}
 ]
}
}, {
 "type":
 "wienerschnitzler",
 "color":
 "#6F5106",
 "caption":
 "Wiener Schnitzler",
 "idno":
 "https://wienerschnitzler.org/tag.html#1903-05-04",
 "head":
 "Wien",
 "desc":
{"listPlace":
  [
 {
 "placeName":
 "I., Innere Stadt",
 "ref":
 ""}
 ,  {
 "placeName":
 "XVIII., Währing",
 "ref":
 ""}
 ,  {
 "placeName":
 "IX., Alsergrund",
 "ref":
 ""}
 ,  {
 "placeName":
 "XIII., Hietzing",
 "ref":
 ""}
 ]
}
}, {
 "type":
 "schnitzler-cmif",
 "subtype":
 "#ya489e21-54d5-40de-a56d-f4548e894428",
 "color":
 "#654321",
 "caption":
 "Gedruckte Briefwechsel",
 "head":
 "Otto Brahm an Arthur Schnitzler, 4.5.1903",
 "source":
 "Der Briefwechsel Arthur Schnitzler – Otto Brahm. Vollständige Ausgabe. Hg., eingel. und erl. von Oskar Seidlin. Tübingen: Niemeyer, 1975."
}] 