[{
 "type":
 "schnitzler-tagebuch",
 "color":
 "#037a33",
 "filename":
 "entry__1906-08-11",
 "caption":
 "Tagebuch",
 "idno":
 "https://schnitzler-tagebuch.acdh.oeaw.ac.at/entry__1906-08-11.html",
 "head":
 "Tagebucheintrag zum 11. August 1906",
 "desc":
{"listPerson":
  [
{
 "persName":
 "Franz Grillparzer",
 "ref":
 "pmb11518"},
 {
 "persName":
 "Elisabeth Steinrück",
 "ref":
 "pmb2315"},
 {
 "persName":
 "Albert Steinrück",
 "ref":
 "pmb12837"}],
 "listBibl":
  [
 {
 "title":
 "Die Poggenpuhls",
 "ref":
 "pmb78375"}
 ,  {
 "title":
 "Grillparzers Briefe und Tagebücher",
 "ref":
 "pmb76989"}
 ],
 "listPlace":
  [
 {
 "placeName":
 "Lübeck",
 "ref":
 "pmb884"}
 ,  {
 "placeName":
 "Kopenhagen",
 "ref":
 "pmb36300"}
 ]
}
}, {
 "type":
 "kalliope-verbund",
 "color":
 "#003574",
 "caption":
 "Kalliope Verbundkatalog",
 "idno":
 "http://kalliope-verbund.info/DE-2498-HS00036243",
 "head":
 "Hecker, Waldemar an Schnitzler, Arthur [Briefe]",
 "text":
 "2 Bl."
}] 