[{
 "type":
 "schnitzler-tagebuch",
 "color":
 "#037a33",
 "filename":
 "entry__1906-02-18",
 "caption":
 "Tagebuch",
 "idno":
 "https://schnitzler-tagebuch.acdh.oeaw.ac.at/entry__1906-02-18.html",
 "head":
 "Tagebucheintrag zum 18. Februar 1906",
 "desc":
{"listPerson":
  [
{
 "persName":
 "Otto Brahm",
 "ref":
 "pmb10986"},
 {
 "persName":
 "Karl Michaelis",
 "ref":
 "pmb3064"},
 {
 "persName":
 "Max Reinhardt",
 "ref":
 "pmb12504"},
 {
 "persName":
 "Rudolf Rittner",
 "ref":
 "pmb12530"},
 {
 "persName":
 "Felix Salten",
 "ref":
 "pmb2167"},
 {
 "persName":
 "Elisabeth Steinrück",
 "ref":
 "pmb2315"},
 {
 "persName":
 "Albert Steinrück",
 "ref":
 "pmb12837"},
 {
 "persName":
 "Jakob Wassermann",
 "ref":
 "pmb13055"}],
 "listBibl":
  [
 {
 "title":
 "Der Ruf des Lebens. Schauspiel in drei Akten",
 "ref":
 "pmb29905"}
 ],
 "listPlace":
  [
 {
 "placeName":
 "",
 "ref":
 "pmb90550"}
 ,  {
 "placeName":
 "Berlin",
 "ref":
 "pmb168"}
 ]
}
}, {
 "type":
 "wienerschnitzler",
 "color":
 "#6F5106",
 "caption":
 "Wiener Schnitzler",
 "idno":
 "https://wienerschnitzler.org/tag.html#1906-02-18",
 "head":
 "Dresden",
 "desc":
{"listPlace":
  [
 {
 "placeName":
 "Hotel Bellevue [Dresden]",
 "ref":
 ""}
 ]
}
}, {
 "type":
 "wienerschnitzler",
 "color":
 "#6F5106",
 "caption":
 "Wiener Schnitzler",
 "idno":
 "https://wienerschnitzler.org/tag.html#1906-02-18",
 "head":
 "Berlin",
 "desc":
{"listPlace":
  [
 {
 "placeName":
 "Hotel Continental [Berlin]",
 "ref":
 ""}
 ,  {
 "placeName":
 "Hotel und Restaurant »Prinz Wilhelm«",
 "ref":
 ""}
 ]
}
}, {
 "type":
 "schnitzler-cmif",
 "subtype":
 "#ya489e21-54d5-40de-a56d-f4548e894428",
 "color":
 "#654321",
 "caption":
 "Gedruckte Briefwechsel",
 "head":
 "Otto Brahm an Arthur Schnitzler, 18.2.1906",
 "source":
 "Der Briefwechsel Arthur Schnitzler – Otto Brahm. Vollständige Ausgabe. Hg., eingel. und erl. von Oskar Seidlin. Tübingen: Niemeyer, 1975."
}] 