[{
 "type":
 "schnitzler-tagebuch",
 "color":
 "#037a33",
 "filename":
 "entry__1908-10-13",
 "caption":
 "Tagebuch",
 "idno":
 "https://schnitzler-tagebuch.acdh.oeaw.ac.at/entry__1908-10-13.html",
 "head":
 "Tagebucheintrag zum 13. Oktober 1908",
 "desc":
{"listPerson":
  [
{
 "persName":
 "Richard Beer-Hofmann",
 "ref":
 "pmb10863"},
 {
 "persName":
 "Louise Schnitzler",
 "ref":
 "pmb12701"},
 {
 "persName":
 "Agnes Ulmann",
 "ref":
 "pmb27942"},
 {
 "persName":
 "Leo Van-Jung",
 "ref":
 "pmb26392"},
 {
 "persName":
 "Jakob Wassermann",
 "ref":
 "pmb13055"},
 {
 "persName":
 "Arthur Kaufmann",
 "ref":
 "pmb2496"}],
 "listBibl":
  [
 {
 "title":
 "Das weite Land. Tragikomödie in fünf Akten",
 "ref":
 "pmb30207"}
 ,  {
 "title":
 "Die Meistersinger von Nürnberg",
 "ref":
 "pmb30661"}
 ,  {
 "title":
 "Die Gefangenen auf der Plassenburg",
 "ref":
 "pmb76944"}
 ]
}
}] 