[{
 "type":
 "schnitzler-tagebuch",
 "color":
 "#037a33",
 "filename":
 "entry__1908-09-10",
 "caption":
 "Tagebuch",
 "idno":
 "https://schnitzler-tagebuch.acdh.oeaw.ac.at/entry__1908-09-10.html",
 "head":
 "Tagebucheintrag zum 10. September 1908",
 "desc":
{"listPerson":
  [
{
 "persName":
 "Paul Brann",
 "ref":
 "pmb10998"},
 {
 "persName":
 "Richard Langner",
 "ref":
 "pmb20111"},
 {
 "persName":
 "Siegfried August Mahlmann",
 "ref":
 "pmb8778"},
 {
 "persName":
 "Octave Mirbeau",
 "ref":
 "pmb8948"},
 {
 "persName":
 "Friedrich Mitterwurzer",
 "ref":
 "pmb12265"},
 {
 "persName":
 "Heinz Monnard",
 "ref":
 "pmb3960"},
 {
 "persName":
 "Johann Ress",
 "ref":
 "pmb23283"},
 {
 "persName":
 "Carl Rössler",
 "ref":
 "pmb4858"},
 {
 "persName":
 "Albert von Speidel",
 "ref":
 "pmb12813"},
 {
 "persName":
 "Elisabeth Steinrück",
 "ref":
 "pmb2315"},
 {
 "persName":
 "Heinrich Traut",
 "ref":
 "pmb26146"},
 {
 "persName":
 "Raoul Walter",
 "ref":
 "pmb10435"},
 {
 "persName":
 "Albert Steinrück",
 "ref":
 "pmb12837"},
 {
 "persName":
 "Margarethe Swoboda",
 "ref":
 "pmb25778"},
 {
 "persName":
 "Emil Birron",
 "ref":
 "pmb10940"},
 {
 "persName":
 "Matthieu Lützenkirchen",
 "ref":
 "pmb20790"},
 {
 "persName":
 "Felix Mottl",
 "ref":
 "pmb12300"}],
 "listBibl":
  [
 {
 "title":
 "Das weite Land. Tragikomödie in fünf Akten",
 "ref":
 "pmb30207"}
 ,  {
 "title":
 "Der Weg ins Freie. Roman",
 "ref":
 "pmb29923"}
 ,  {
 "title":
 "Zwischenspiel. Komödie in drei Akten",
 "ref":
 "pmb29903"}
 ,  {
 "title":
 "König Violon und Prinzessin Klarinette",
 "ref":
 "pmb80947"}
 ,  {
 "title":
 "La 628-E 8",
 "ref":
 "pmb77320"}
 ],
 "listPlace":
  [
 {
 "placeName":
 "Gedonstraße",
 "ref":
 "pmb50607"}
 ]
}
}, {
 "type":
 "wienerschnitzler",
 "color":
 "#6F5106",
 "caption":
 "Wiener Schnitzler",
 "idno":
 "https://wienerschnitzler.org/tag.html#1908-09-10",
 "head":
 "München",
 "desc":
{"listPlace":
  [
 {
 "placeName":
 "Hotel Vier Jahreszeiten",
 "ref":
 ""}
 ,  {
 "placeName":
 "Königlich Bayerische Hoftheater",
 "ref":
 ""}
 ,  {
 "placeName":
 "Heinrich Traut, photographisches Atelier",
 "ref":
 ""}
 ,  {
 "placeName":
 "Gedonstraße 6",
 "ref":
 ""}
 ,  {
 "placeName":
 "Residenztheater München",
 "ref":
 ""}
 ,  {
 "placeName":
 "Odeon-Bar",
 "ref":
 ""}
 ]
}
}, {
 "type":
 "URL",
 "subtype":
 "schnitzler-kultur",
 "filename":
 "pmb209516",
 "idno":
 "https://schnitzler-kultur.acdh.oeaw.ac.at/pmb209516.html",
 "head":
 "Aufführung von Zwischenspiel, 10.9.1908",
 "desc":
{"listBibl":
  [
 {
 "title":
 "Zwischenspiel. Komödie in drei Akten",
 "ref":
 ""}
 ],
 "listPerson":
  [
{
 "persName":
 "Arthur Schnitzler",
 "ref":
 ""}],
 "listPlace":
  [
 {
 "placeName":
 "Residenztheater München",
 "ref":
 ""}
 ]
}
}, {
 "type":
 "schnitzler-interviews",
 "color":
 "#3D5A80",
 "filename":
 "M181",
 "caption":
 "Interviews",
 "idno":
 "https://schnitzler-interviews.acdh.oeaw.ac.at/M181.html",
 "head":
 "Schnitzler: [Über Tolstoj], 10. 9. 1908",
 "desc":
{"listPerson":
  [
{
 "persName":
 "Vasilij Michailowitsch Sobolevskij",
 "ref":
 "pmb25069"},
 {
 "persName":
 "Leo N. von Tolstoi",
 "ref":
 "pmb3739"}],
 "listBibl":
  [
 {
 "title":
 "An die Redaktion der Russkje Wedomosti",
 "ref":
 "pmb88385"}
 ,  {
 "title":
 "Russkije vedomosti",
 "ref":
 "pmb61629"}
 ],
 "listOrg":
  [
 {
 "orgName":
 "Russkije vedomosti",
 "ref":
 "pmb60847"}
 ]
}
}] 