[{
 "type":
 "schnitzler-tagebuch",
 "color":
 "#037a33",
 "filename":
 "entry__1910-03-02",
 "caption":
 "Tagebuch",
 "idno":
 "https://schnitzler-tagebuch.acdh.oeaw.ac.at/entry__1910-03-02.html",
 "head":
 "Tagebucheintrag zum 2. März 1910",
 "desc":
{"listPerson":
  [
{
 "persName":
 "Ludwig van Beethoven",
 "ref":
 "pmb10866"},
 {
 "persName":
 "Johannes Brahms",
 "ref":
 "pmb10989"},
 {
 "persName":
 "Max Kalbeck",
 "ref":
 "pmb11857"},
 {
 "persName":
 "Leon Kellner",
 "ref":
 "pmb11904"},
 {
 "persName":
 "William Shakespeare",
 "ref":
 "pmb2412"},
 {
 "persName":
 "Josef von Winter",
 "ref":
 "pmb13129"},
 {
 "persName":
 "Wilhelmine Schubert",
 "ref":
 "pmb24531"},
 {
 "persName":
 "Franz Peter Schubert",
 "ref":
 "pmb12729"}],
 "listBibl":
  [
 {
 "title":
 "Frau Beate und ihr Sohn. Novelle",
 "ref":
 "pmb32133"}
 ,  {
 "title":
 "Der Weg ins Freie. Roman",
 "ref":
 "pmb29923"}
 ,  {
 "title":
 "Walzerreigen",
 "ref":
 "pmb77660"}
 ],
 "listPlace":
  [
 {
 "placeName":
 "Messerschmidtgasse",
 "ref":
 "pmb60068"}
 ,  {
 "placeName":
 "",
 "ref":
 "pmb532"}
 ,  {
 "placeName":
 "Pötzleinsdorf",
 "ref":
 "pmb169"}
 ]
}
}, {
 "type":
 "wienerschnitzler",
 "color":
 "#6F5106",
 "caption":
 "Wiener Schnitzler",
 "idno":
 "https://wienerschnitzler.org/tag.html#1910-03-02",
 "head":
 "Wien",
 "desc":
{"listPlace":
  [
 {
 "placeName":
 "XVII., Hernals",
 "ref":
 ""}
 ,  {
 "placeName":
 "XVIII., Währing",
 "ref":
 ""}
 ]
}
}] 