[{
 "type":
 "schnitzler-tagebuch",
 "color":
 "#037a33",
 "filename":
 "entry__1910-04-13",
 "caption":
 "Tagebuch",
 "idno":
 "https://schnitzler-tagebuch.acdh.oeaw.ac.at/entry__1910-04-13.html",
 "head":
 "Tagebuch, 13. April 1910",
 "desc":
{"listPerson":
  [
{
 "persName":
 "Alfred von Berger",
 "ref":
 "person_13624"},
 {
 "persName":
 "Otto Tressler",
 "ref":
 "person_20803"},
 {
 "persName":
 "Carl von Zeska",
 "ref":
 "person_21543"}],
 "listBibl":
  [
 {
 "title":
 "Frau Beate und ihr Sohn. Novelle",
 "ref":
 "pmb32133"}
 ,  {
 "title":
 "Liebelei. Schauspiel in drei Akten",
 "ref":
 "pmb29917"}
 ]
}
}, {
 "type":
 "wienerschnitzler",
 "color":
 "#6F5106",
 "caption":
 "Wiener Schnitzler",
 "idno":
 "https://wienerschnitzler.org/tag.html#1910-04-13",
 "head":
 "Wien",
 "desc":
{"listPlace":
  [
 {
 "placeName":
 "I., Innere Stadt",
 "ref":
 ""}
 ,  {
 "placeName":
 "XVIII., Währing",
 "ref":
 ""}
 ]
}
}, {
 "type":
 "URL",
 "subtype":
 "schnitzler-kultur",
 "filename":
 "pmb249956",
 "idno":
 "https://schnitzler-kultur.acdh.oeaw.ac.at/pmb249956.html",
 "head":
 "Probe von Liebelei, 13.4.1910",
 "desc":
{"listOrg":
  [
 {
 "orgName":
 "Burgtheater",
 "ref":
 ""}
 ],
 "listBibl":
  [
 {
 "title":
 "Liebelei. Schauspiel in drei Akten",
 "ref":
 ""}
 ],
 "listPerson":
  [
{
 "persName":
 "Arthur Schnitzler",
 "ref":
 ""}],
 "listPlace":
  [
 {
 "placeName":
 "Burgtheater",
 "ref":
 ""}
 ]
}
}, {
 "type":
 "schnitzler-fischer",
 "color":
 "#3D4F9F",
 "caption":
 "Schnitzler – S. Fischer",
 "idno":
 "https://biblio.ub.uni-freiburg.de/sf/details/10310",
 "head":
 "Samuel Fischer an Arthur Schnitzler, 1910-04-13",
 "desc":
{"listPerson":
  [
{
 "persName":
 "Samuel Fischer",
 "ref":
 "#pmb11324"},
 {
 "persName":
 "Arthur Schnitzler",
 "ref":
 "#pmb2121"}],
 "listPerson":
  [
{
 "persName":
 "Samuel Fischer",
 "ref":
 "#pmb11324"},
 {
 "persName":
 "Karl Walser",
 "ref":
 "#pmb13037"},
 {
 "persName":
 "Alice Kauser",
 "ref":
 "#pmb19236"},
 {
 "persName":
 "Theodor Etzel",
 "ref":
 "#pmb61404"}],
 "listBibl":
  [
 {
 "title":
 "Der grüne Kakadu. Groteske in einem Akt",
 "ref":
 "#pmb29843"}
 ,  {
 "title":
 "Der Schleier der Beatrice. Schauspiel in fünf Akten",
 "ref":
 "#pmb29857"}
 ,  {
 "title":
 "Lebendige Stunden. Vier Einakter",
 "ref":
 "#pmb29863"}
 ,  {
 "title":
 "Die Frau mit dem Dolche",
 "ref":
 "#pmb29865"}
 ,  {
 "title":
 "Der junge Medardus. Dramatische Historie in einem Vorspiel und fünf Aufzügen",
 "ref":
 "#pmb29937"}
 ,  {
 "title":
 "Zum großen Wurstel. Burleske in einem Akt",
 "ref":
 "#pmb29951"}
 ,  {
 "title":
 "Welthumor",
 "ref":
 "#pmb335609"}
 ],
 "listPlace":
  [
 {
 "placeName":
 "Berlin",
 "ref":
 "#pmb168"}
 ,  {
 "placeName":
 "Vereinigte Staaten von Amerika [USA]",
 "ref":
 "#pmb43406"}
 ,  {
 "placeName":
 "New York City",
 "ref":
 "#pmb44053"}
 ,  {
 "placeName":
 "Wien",
 "ref":
 "#pmb50"}
 ]
}
}, {
 "type":
 "schnitzler-cmif",
 "subtype":
 "#s364f351-b14a-4d77-b480-295e58878c66",
 "color":
 "#654321",
 "caption":
 "Gedruckte Briefwechsel",
 "head":
 "Samuel Fischer an Arthur Schnitzler, 13.4.1910",
 "source":
 "Hans Peter Buohler: Arthur Schnitzlers »Medardus Affairen« Teil 1: Korrespondenzen. In: Hofmannsthal-Jahrbuch ⋅ Zur europäischen Moderne, Jg. 19 (2011), S. 79–215."
}] 