[{
 "type":
 "schnitzler-tagebuch",
 "color":
 "#037a33",
 "filename":
 "entry__1910-07-17",
 "caption":
 "Tagebuch",
 "idno":
 "https://schnitzler-tagebuch.acdh.oeaw.ac.at/entry__1910-07-17.html",
 "head":
 "Tagebucheintrag zum 17. Juli 1910",
 "desc":
{"listPerson":
  [
{
 "persName":
 "Richard Beer-Hofmann",
 "ref":
 "pmb10863"},
 {
 "persName":
 "Alfred von Berger",
 "ref":
 "pmb10883"},
 {
 "persName":
 "Lili Cappellini",
 "ref":
 "pmb2238"},
 {
 "persName":
 "Karl Kraus",
 "ref":
 "pmb11988"},
 {
 "persName":
 "Ernestine Lothar",
 "ref":
 "pmb20612"},
 {
 "persName":
 "Rudolf Lothar",
 "ref":
 "pmb2570"},
 {
 "persName":
 "Ferdinand Schmutzer",
 "ref":
 "pmb12689"},
 {
 "persName":
 "Adolf von Sonnenthal",
 "ref":
 "pmb12809"},
 {
 "persName":
 "Max von Gutmann",
 "ref":
 "pmb17579"},
 {
 "persName":
 "Arthur Kaufmann",
 "ref":
 "pmb2496"},
 {
 "persName":
 "Gustav Mahler",
 "ref":
 "pmb12163"},
 {
 "persName":
 "Frieda Pollak",
 "ref":
 "pmb22728"}],
 "listBibl":
  [
 {
 "title":
 "Das weite Land. Tragikomödie in fünf Akten",
 "ref":
 "pmb30207"}
 ,  {
 "title":
 "Im Vaterhaus",
 "ref":
 "pmb76860"}
 ,  {
 "title":
 "Die Fackel",
 "ref":
 "pmb41244"}
 ],
 "listPlace":
  [
 {
 "placeName":
 "Wien",
 "ref":
 "pmb50"}
 ,  {
 "placeName":
 "Virgl",
 "ref":
 "pmb92584"}
 ,  {
 "placeName":
 "Wilten",
 "ref":
 "pmb49502"}
 ,  {
 "placeName":
 "Gentzgasse",
 "ref":
 "pmb40694"}
 ,  {
 "placeName":
 "Lazaristengasse",
 "ref":
 "pmb40076"}
 ,  {
 "placeName":
 "Kahlenberg",
 "ref":
 "pmb574"}
 ,  {
 "placeName":
 "Türkenschanzpark",
 "ref":
 "pmb113"}
 ]
}
}, {
 "type":
 "schnitzler-traeume",
 "subtype":
 "#ISBN978-3-8353-1029-2",
 "color":
 "#1193CC",
 "caption":
 "Traumtagebuch",
 "head":
 "Traum vom 17. Juli 1910",
 "source":
 "Arthur Schnitzler: Träume. Das Traumtagebuch 1875–1931. Herausgegeben von Peter Michael Braunwarth und Leo A. Lensing. Göttingen: Wallstein 2012 (Bibliothek Janowitz, Bd. 20)"
}] 