[{
 "type":
 "schnitzler-tagebuch",
 "color":
 "#037a33",
 "filename":
 "entry__1911-07-03",
 "caption":
 "Tagebuch",
 "idno":
 "https://schnitzler-tagebuch.acdh.oeaw.ac.at/entry__1911-07-03.html",
 "head":
 "Tagebucheintrag zum 3. Juli 1911",
 "desc":
{"listPerson":
  [
{
 "persName":
 "Stefanie Bachrach",
 "ref":
 "pmb13653"},
 {
 "persName":
 "Otto Brahm",
 "ref":
 "pmb10986"},
 {
 "persName":
 "Gertrude von Hofmannsthal",
 "ref":
 "pmb2292"},
 {
 "persName":
 "Elisabeth Steinrück",
 "ref":
 "pmb2315"},
 {
 "persName":
 "Clara Jonas",
 "ref":
 "pmb18900"},
 {
 "persName":
 "Albert Steinrück",
 "ref":
 "pmb12837"},
 {
 "persName":
 "Jakob Wassermann",
 "ref":
 "pmb13055"},
 {
 "persName":
 "Hugo von Hofmannsthal",
 "ref":
 "pmb11740"},
 {
 "persName":
 "Herman Kroepelin",
 "ref":
 "pmb8351"}],
 "listBibl":
  [
 {
 "title":
 "Komödiantin",
 "ref":
 "pmb36101"}
 ,  {
 "title":
 "Harte Ehen. Roman",
 "ref":
 "pmb78942"}
 ,  {
 "title":
 "Jean-Christophe",
 "ref":
 "pmb78079"}
 ],
 "listPlace":
  [
 {
 "placeName":
 "Wolfsbergkogel",
 "ref":
 "pmb92607"}
 ]
}
}, {
 "type":
 "wienerschnitzler",
 "color":
 "#6F5106",
 "caption":
 "Wiener Schnitzler",
 "idno":
 "https://wienerschnitzler.org/tag.html#1911-07-03",
 "head":
 "Semmering",
 "desc":
{"listPlace":
  [
 {
 "placeName":
 "Südbahnhotel [Semmering]",
 "ref":
 ""}
 ,  {
 "placeName":
 "Bahnhof Semmering",
 "ref":
 ""}
 ,  {
 "placeName":
 "Wolfsbergkogel",
 "ref":
 ""}
 ]
}
}, {
 "type":
 "wienerschnitzler",
 "color":
 "#6F5106",
 "caption":
 "Wiener Schnitzler",
 "idno":
 "https://wienerschnitzler.org/tag.html#1911-07-03",
 "head":
 "Wien",
 "desc":
{"listPlace":
  [
 {
 "placeName":
 "X., Favoriten",
 "ref":
 ""}
 ,  {
 "placeName":
 "XVIII., Währing",
 "ref":
 ""}
 ]
}
}, {
 "type":
 "kalliope-verbund",
 "color":
 "#003574",
 "caption":
 "Kalliope Verbundkatalog",
 "idno":
 "http://kalliope-verbund.info/DE-2498-HS00084413",
 "head":
 "Schnitzler, Arthur: Komödiantin [Dramatisches] (Drucktitel)",
 "text":
 "Erstes Objekt aus der Mappe. 3 Bl."
}] 