[{
 "type":
 "schnitzler-tagebuch",
 "color":
 "#037a33",
 "filename":
 "entry__1912-12-26",
 "caption":
 "Tagebuch",
 "idno":
 "https://schnitzler-tagebuch.acdh.oeaw.ac.at/entry__1912-12-26.html",
 "head":
 "Tagebucheintrag zum 26. Dezember 1912",
 "desc":
{"listPerson":
  [
{
 "persName":
 "Stefanie Bachrach",
 "ref":
 "pmb13653"},
 {
 "persName":
 "Heinrich Schnitzler",
 "ref":
 "pmb12692"},
 {
 "persName":
 "Johann Schnitzler",
 "ref":
 "pmb12695"},
 {
 "persName":
 "Wolfgang Schumann",
 "ref":
 "pmb9786"},
 {
 "persName":
 "Jakob Wassermann",
 "ref":
 "pmb13055"},
 {
 "persName":
 "Arthur Wilheim",
 "ref":
 "pmb27131"}],
 "listBibl":
  [
 {
 "title":
 "Herbot",
 "ref":
 "pmb35894"}
 ,  {
 "title":
 "Professor Bernhardi. Komödie in fünf Akten",
 "ref":
 "pmb30203"}
 ,  {
 "title":
 "Der Vorige",
 "ref":
 "pmb30781"}
 ,  {
 "title":
 "Das Gänsemännchen. Roman",
 "ref":
 "pmb30899"}
 ],
 "listPlace":
  [
 {
 "placeName":
 "Afrika",
 "ref":
 "pmb49098"}
 ,  {
 "placeName":
 "Landstraßer Hauptstraße",
 "ref":
 "pmb50530"}
 ]
}
}, {
 "type":
 "URL",
 "subtype":
 "schnitzler-kultur",
 "filename":
 "pmb254070",
 "idno":
 "https://schnitzler-kultur.acdh.oeaw.ac.at/pmb254070.html",
 "head":
 "Private Lesung von Herbot, 26.12.1912",
 "desc":
{"listBibl":
  [
 {
 "title":
 "Herbot",
 "ref":
 ""}
 ],
 "listPerson":
  [
{
 "persName":
 "Arthur Schnitzler",
 "ref":
 ""},
 {
 "persName":
 "Olga Schnitzler",
 "ref":
 ""}],
 "listPlace":
  [
 {
 "placeName":
 "Sternwartestraße 71",
 "ref":
 ""}
 ]
}
}, {
 "type":
 "schnitzler-traeume",
 "subtype":
 "#ISBN978-3-8353-1029-2",
 "color":
 "#1193CC",
 "caption":
 "Traumtagebuch",
 "head":
 "Traum vom 26. Dezember 1912",
 "source":
 "Arthur Schnitzler: Träume. Das Traumtagebuch 1875–1931. Herausgegeben von Peter Michael Braunwarth und Leo A. Lensing. Göttingen: Wallstein 2012 (Bibliothek Janowitz, Bd. 20)"
}] 