[{
 "type":
 "schnitzler-tagebuch",
 "color":
 "#037a33",
 "filename":
 "entry__1912-08-24",
 "caption":
 "Tagebuch",
 "idno":
 "https://schnitzler-tagebuch.acdh.oeaw.ac.at/entry__1912-08-24.html",
 "head":
 "Tagebuch, 24. August 1912",
 "desc":
{"listPerson":
  [
{
 "persName":
 "Alfred von Berger",
 "ref":
 "person_13624"},
 {
 "persName":
 "Franz Colmers",
 "ref":
 "person_14259"},
 {
 "persName":
 "Paul Kupelwieser",
 "ref":
 "person_17207"},
 {
 "persName":
 "Heinrich Prechtler",
 "ref":
 "person_18950"},
 {
 "persName":
 "Hugo Schmidl",
 "ref":
 "person_19755"},
 {
 "persName":
 "Otto Zuckerkandl",
 "ref":
 "person_21601"},
 {
 "persName":
 "Ferdinande Schmittlein",
 "ref":
 "person_19778"}],
 "listPlace":
  [
 {
 "placeName":
 "Pola",
 "ref":
 "pmb851"}
 ,  {
 "placeName":
 "Trieste",
 "ref":
 "pmb91944"}
 ,  {
 "placeName":
 "Villach",
 "ref":
 "pmb92011"}
 ]
}
}, {
 "type":
 "wienerschnitzler",
 "color":
 "#6F5106",
 "caption":
 "Wiener Schnitzler",
 "idno":
 "https://wienerschnitzler.org/tag.html#1912-08-24",
 "head":
 "Brijuni",
 "desc":
{"listPlace":
  [
 {
 "placeName":
 "Hotel Neptun III",
 "ref":
 ""}
 ]
}
}, {
 "type":
 "wienerschnitzler",
 "color":
 "#6F5106",
 "caption":
 "Wiener Schnitzler",
 "idno":
 "https://wienerschnitzler.org/tag.html#1912-08-24",
 "head":
 "Villach",
 "desc":
{"listPlace":
  [
 {
 "placeName":
 "Parkhotel Villach",
 "ref":
 ""}
 ]
}
}, {
 "type":
 "wienerschnitzler",
 "color":
 "#6F5106",
 "caption":
 "Wiener Schnitzler",
 "idno":
 "https://wienerschnitzler.org/tag.html#1912-08-24",
 "head":
 "Triest",
 "desc":
{"listPlace":
  [
 {
 "placeName":
 "Savoia Excelsior Palace",
 "ref":
 ""}
 ,  {
 "placeName":
 "Triest Hauptbahnhof",
 "ref":
 ""}
 ]
}
}, {
 "type":
 "wienerschnitzler",
 "color":
 "#6F5106",
 "caption":
 "Wiener Schnitzler",
 "idno":
 "https://wienerschnitzler.org/tag.html#1912-08-24",
 "head":
 "Pula",
 "desc":
{"listPlace":
  [
 {
 "placeName":
 "Arena",
 "ref":
 ""}
 ]
}
}, {
 "type":
 "schnitzler-fischer",
 "color":
 "#3D4F9F",
 "caption":
 "Schnitzler – S. Fischer",
 "idno":
 "https://biblio.ub.uni-freiburg.de/sf/details/10454",
 "head":
 "Samuel Fischer, Carl Schur an Arthur Schnitzler, 1912-08-24",
 "desc":
{"listPerson":
  [
{
 "persName":
 "Samuel Fischer",
 "ref":
 "#pmb11324"},
 {
 "persName":
 "Carl Schur",
 "ref":
 "#pmb335601"},
 {
 "persName":
 "Arthur Schnitzler",
 "ref":
 "#pmb2121"}],
 "listPerson":
  [
{
 "persName":
 "Ada Sestan",
 "ref":
 "#pmb104772"},
 {
 "persName":
 "Samuel Fischer",
 "ref":
 "#pmb11324"},
 {
 "persName":
 "Gerolamo Enrico Nani",
 "ref":
 "#pmb21787"},
 {
 "persName":
 "Emil Thieben",
 "ref":
 "#pmb25995"},
 {
 "persName":
 "Oskar Friedrich Eirich",
 "ref":
 "#pmb2874"},
 {
 "persName":
 "Carl Schur",
 "ref":
 "#pmb335601"},
 {
 "persName":
 "Willi Dias",
 "ref":
 "#pmb336635"}],
 "listBibl":
  [
 {
 "title":
 "Der grüne Kakadu. Groteske in einem Akt",
 "ref":
 "#pmb29843"}
 ,  {
 "title":
 "Reigen. Zehn Dialoge",
 "ref":
 "#pmb29855"}
 ,  {
 "title":
 "Zwischenspiel. Komödie in drei Akten",
 "ref":
 "#pmb29903"}
 ,  {
 "title":
 "Der Ruf des Lebens. Schauspiel in drei Akten",
 "ref":
 "#pmb29905"}
 ,  {
 "title":
 "Liebelei. Schauspiel in drei Akten",
 "ref":
 "#pmb29917"}
 ,  {
 "title":
 "Der einsame Weg. Schauspiel in fünf Akten",
 "ref":
 "#pmb29985"}
 ],
 "listPlace":
  [
 {
 "placeName":
 "Berlin",
 "ref":
 "#pmb168"}
 ,  {
 "placeName":
 "Ungarn",
 "ref":
 "#pmb35512"}
 ,  {
 "placeName":
 "Italien",
 "ref":
 "#pmb40306"}
 ,  {
 "placeName":
 "Budapest",
 "ref":
 "#pmb43471"}
 ,  {
 "placeName":
 "Brijuni",
 "ref":
 "#pmb45260"}
 ,  {
 "placeName":
 "Triest",
 "ref":
 "#pmb873"}
 ,  {
 "placeName":
 "Mailand",
 "ref":
 "#pmb886"}
 ]
}
}] 