[{
 "type":
 "schnitzler-tagebuch",
 "color":
 "#037a33",
 "filename":
 "entry__1913-03-22",
 "caption":
 "Tagebuch",
 "idno":
 "https://schnitzler-tagebuch.acdh.oeaw.ac.at/entry__1913-03-22.html",
 "head":
 "Tagebucheintrag zum 22. März 1913",
 "desc":
{"listPerson":
  [
{
 "persName":
 "Stefanie Bachrach",
 "ref":
 "pmb13653"},
 {
 "persName":
 "Richard Beer-Hofmann",
 "ref":
 "pmb10863"},
 {
 "persName":
 "Habsburg",
 "ref":
 "pmb17702"},
 {
 "persName":
 "Alexander von? Popper-Podhragy",
 "ref":
 "pmb22803"},
 {
 "persName":
 "Emil Reich",
 "ref":
 "pmb9449"},
 {
 "persName":
 "Marianne Zuckerkandl",
 "ref":
 "pmb2753"},
 {
 "persName":
 "Nicolas Rétif de la Bretonne",
 "ref":
 "pmb3978"},
 {
 "persName":
 "Paula Beer-Hofmann",
 "ref":
 "pmb10860"},
 {
 "persName":
 "Wilhelm Bode",
 "ref":
 "pmb10969"},
 {
 "persName":
 "Alfons Petzold",
 "ref":
 "pmb9239"}],
 "listBibl":
  [
 {
 "title":
 "Stunde des Erkennens",
 "ref":
 "pmb31447"}
 ,  {
 "title":
 "Charlotte von Stein",
 "ref":
 "pmb78114"}
 ,  {
 "title":
 "Brehms Tierleben",
 "ref":
 "pmb30011"}
 ,  {
 "title":
 "Les contemporaines",
 "ref":
 "pmb78420"}
 ,  {
 "title":
 "Briefwechsel zwischen Varnhagen und Rahel",
 "ref":
 "pmb76537"}
 ],
 "listPlace":
  [
 {
 "placeName":
 "",
 "ref":
 "pmb91735"}
 ]
}
}] 