[{
 "type":
 "schnitzler-tagebuch",
 "color":
 "#037a33",
 "filename":
 "entry__1913-03-26",
 "caption":
 "Tagebuch",
 "idno":
 "https://schnitzler-tagebuch.acdh.oeaw.ac.at/entry__1913-03-26.html",
 "head":
 "Tagebucheintrag zum 26. März 1913",
 "desc":
{"listPerson":
  [
{
 "persName":
 "Franz Dülberg",
 "ref":
 "pmb6910"},
 {
 "persName":
 "Helene Ritscher",
 "ref":
 "pmb2303"},
 {
 "persName":
 "Rudolf Rittner",
 "ref":
 "pmb12530"}],
 "listBibl":
  [
 {
 "title":
 "Flucht in die Finsternis",
 "ref":
 "pmb30863"}
 ,  {
 "title":
 "Korallenkettlin. Schauspiel in drei Akten",
 "ref":
 "pmb80386"}
 ],
 "listPlace":
  [
 {
 "placeName":
 "VIII., Josefstadt",
 "ref":
 "pmb58"}
 ,  {
 "placeName":
 "Berlin",
 "ref":
 "pmb168"}
 ]
}
}, {
 "type":
 "URL",
 "subtype":
 "schnitzler-kultur",
 "filename":
 "pmb254292",
 "idno":
 "https://schnitzler-kultur.acdh.oeaw.ac.at/pmb254292.html",
 "head":
 "Premiere von Korallenkettlin, 26.3.1913",
 "desc":
{"listOrg":
  [
 {
 "orgName":
 "Theater in der Josefstadt",
 "ref":
 ""}
 ],
 "listBibl":
  [
 {
 "title":
 "Korallenkettlin. Schauspiel in drei Akten",
 "ref":
 ""}
 ],
 "listPerson":
  [
{
 "persName":
 "Arthur Schnitzler",
 "ref":
 ""}],
 "listPlace":
  [
 {
 "placeName":
 "Theater in der Josefstadt",
 "ref":
 ""}
 ]
}
}, {
 "type":
 "kalliope-verbund",
 "color":
 "#003574",
 "caption":
 "Kalliope Verbundkatalog",
 "idno":
 "http://kalliope-verbund.info/DE-2498-HS00077613",
 "head":
 "Gangnus, A. an Schnitzler, Arthur [Briefe]",
 "text":
 "1 Bl."
}] 