[{
 "type":
 "schnitzler-tagebuch",
 "color":
 "#037a33",
 "filename":
 "entry__1914-07-01",
 "caption":
 "Tagebuch",
 "idno":
 "https://schnitzler-tagebuch.acdh.oeaw.ac.at/entry__1914-07-01.html",
 "head":
 "Tagebucheintrag zum 1. Juli 1914",
 "desc":
{"listPerson":
  [
{
 "persName":
 "Franz Ferdinand von Österreich-Este",
 "ref":
 "pmb3287"},
 {
 "persName":
 "Franz Joseph I. von Österreich-Ungarn",
 "ref":
 "pmb2513"},
 {
 "persName":
 "Alfred Gerasch",
 "ref":
 "pmb11423"},
 {
 "persName":
 "Richard Rosenbaum",
 "ref":
 "pmb12556"},
 {
 "persName":
 "Tr.",
 "ref":
 "pmb26131"},
 {
 "persName":
 "Else Wohlgemuth",
 "ref":
 "pmb12951"}],
 "listBibl":
  [
 {
 "title":
 "Doktor Gräsler, Badearzt",
 "ref":
 "pmb30201"}
 ,  {
 "title":
 "Heimkehr",
 "ref":
 "pmb36091"}
 ],
 "listPlace":
  [
 {
 "placeName":
 "Pötzleinsdorf",
 "ref":
 "pmb169"}
 ]
}
}] 