[{
 "type":
 "schnitzler-tagebuch",
 "color":
 "#037a33",
 "filename":
 "entry__1914-02-27",
 "caption":
 "Tagebuch",
 "idno":
 "https://schnitzler-tagebuch.acdh.oeaw.ac.at/entry__1914-02-27.html",
 "head":
 "Tagebucheintrag zum 27. Februar 1914",
 "desc":
{"listPerson":
  [
{
 "persName":
 "Giovanni Bellini",
 "ref":
 "pmb13955"},
 {
 "persName":
 "Lili Cappellini",
 "ref":
 "pmb2238"},
 {
 "persName":
 "Franz von Dirsztay",
 "ref":
 "pmb15406"},
 {
 "persName":
 "Karl Grosz",
 "ref":
 "pmb17431"},
 {
 "persName":
 "Albert Paris Gütersloh",
 "ref":
 "pmb11558"},
 {
 "persName":
 "Emma Gütersloh",
 "ref":
 "pmb17640"},
 {
 "persName":
 "Karl Kraus",
 "ref":
 "pmb11988"},
 {
 "persName":
 "Erwin Lang",
 "ref":
 "pmb8463"},
 {
 "persName":
 "Alma Maria Mahler-Werfel",
 "ref":
 "pmb12160"},
 {
 "persName":
 "Maria Mayer",
 "ref":
 "pmb4061"},
 {
 "persName":
 "Carl Moll",
 "ref":
 "pmb12277"},
 {
 "persName":
 "Lilly Roth",
 "ref":
 "pmb23646"},
 {
 "persName":
 "Hugo Schmidl",
 "ref":
 "pmb3159"},
 {
 "persName":
 "Adolf von Sonnenthal",
 "ref":
 "pmb12809"},
 {
 "persName":
 "Julie Wassermann",
 "ref":
 "pmb13058"},
 {
 "persName":
 "Grethe Wiesenthal",
 "ref":
 "pmb27100"},
 {
 "persName":
 "Berta Zuckerkandl",
 "ref":
 "pmb2312"},
 {
 "persName":
 "Emil Roth",
 "ref":
 "pmb23641"},
 {
 "persName":
 "Johann Schnitzler",
 "ref":
 "pmb12695"},
 {
 "persName":
 "Jakob Wassermann",
 "ref":
 "pmb13055"},
 {
 "persName":
 "Jürgen Fehling",
 "ref":
 "pmb7102"},
 {
 "persName":
 "Gustav Mahler",
 "ref":
 "pmb12163"},
 {
 "persName":
 "Giovanni Battista Tiepolo",
 "ref":
 "pmb10225"},
 {
 "persName":
 "Jacobo Tintoretto",
 "ref":
 "pmb3173"},
 {
 "persName":
 "Victor Zuckerkandl",
 "ref":
 "pmb54787"}],
 "listBibl":
  [
 {
 "title":
 "Fink und Fliederbusch. Komödie in drei Akten",
 "ref":
 "pmb30881"}
 ],
 "listPlace":
  [
 {
 "placeName":
 "Burgtheater",
 "ref":
 "pmb14"}
 ,  {
 "placeName":
 "Sankt Petersburg",
 "ref":
 "pmb433"}
 ]
}
}, {
 "type":
 "wienerschnitzler",
 "color":
 "#6F5106",
 "caption":
 "Wiener Schnitzler",
 "idno":
 "https://wienerschnitzler.org/tag.html#1914-02-27",
 "head":
 "Wien",
 "desc":
{"listPlace":
  [
 {
 "placeName":
 "XIX., Döbling",
 "ref":
 ""}
 ,  {
 "placeName":
 "XVIII., Währing",
 "ref":
 ""}
 ]
}
}, {
 "type":
 "schnitzler-fischer",
 "color":
 "#3D4F9F",
 "caption":
 "Schnitzler – S. Fischer",
 "idno":
 "https://biblio.ub.uni-freiburg.de/sf/details/10521",
 "head":
 "Samuel Fischer, Ernst Peter Tal an Arthur Schnitzler, 1914-02-27",
 "desc":
{"listPerson":
  [
{
 "persName":
 "Samuel Fischer",
 "ref":
 "#pmb11324"},
 {
 "persName":
 "Ernst Peter Tal",
 "ref":
 "#pmb4621"},
 {
 "persName":
 "Arthur Schnitzler",
 "ref":
 "#pmb2121"}],
 "listPerson":
  [
{
 "persName":
 "Samuel Fischer",
 "ref":
 "#pmb11324"},
 {
 "persName":
 "Ernst Peter Tal",
 "ref":
 "#pmb4621"},
 {
 "persName":
 "Hans Kyser",
 "ref":
 "#pmb8386"}],
 "listBibl":
  [
 {
 "title":
 "Erziehung zur Liebe. Ein ernstes Spiel in vier Akten.",
 "ref":
 "#pmb335741"}
 ],
 "listPlace":
  [
 {
 "placeName":
 "Berlin",
 "ref":
 "#pmb168"}
 ,  {
 "placeName":
 "Wien",
 "ref":
 "#pmb50"}
 ]
}
}, {
 "type":
 "schnitzler-fischer",
 "color":
 "#3D4F9F",
 "caption":
 "Schnitzler – S. Fischer",
 "idno":
 "https://biblio.ub.uni-freiburg.de/sf/details/10522",
 "head":
 "Samuel Fischer, Lothar Schmidt an Arthur Schnitzler, 1914-02-27",
 "desc":
{"listPerson":
  [
{
 "persName":
 "Samuel Fischer",
 "ref":
 "#pmb11324"},
 {
 "persName":
 "Lothar Schmidt",
 "ref":
 "#pmb12681"},
 {
 "persName":
 "Arthur Schnitzler",
 "ref":
 "#pmb2121"}],
 "listPerson":
  [
{
 "persName":
 "Samuel Fischer",
 "ref":
 "#pmb11324"},
 {
 "persName":
 "Lothar Schmidt",
 "ref":
 "#pmb12681"},
 {
 "persName":
 "Johanne Skram-Knudsen",
 "ref":
 "#pmb336347"}],
 "listBibl":
  [
 {
 "title":
 "Lieutenant Gustl. Novelle",
 "ref":
 "#pmb29853"}
 ,  {
 "title":
 "Excentric",
 "ref":
 "#pmb29893"}
 ,  {
 "title":
 "Die griechische Tänzerin. Novellette",
 "ref":
 "#pmb30167"}
 ],
 "listPlace":
  [
 {
 "placeName":
 "Berlin",
 "ref":
 "#pmb168"}
 ,  {
 "placeName":
 "Dänemark",
 "ref":
 "#pmb43570"}
 ,  {
 "placeName":
 "Wien",
 "ref":
 "#pmb50"}
 ]
}
}, {
 "type":
 "schnitzler-cmif",
 "subtype":
 "#dc95034c-3e70-47e1-9072-3fc75d84b47a",
 "color":
 "#654321",
 "caption":
 "Gedruckte Briefwechsel",
 "head":
 "Fritz Unruh an Arthur Schnitzler, 27.2.1914",
 "source":
 "Ulrich K. Goldsmith: Der Briefwechsel Fritz von Unruhs mit Arthur Schnitzler. In: Modern Austrian Literature, Jg. 10, 1977, H. 3/4, S. 69-128."
}] 