[{
 "type":
 "schnitzler-tagebuch",
 "color":
 "#037a33",
 "filename":
 "entry__1915-06-28",
 "caption":
 "Tagebuch",
 "idno":
 "https://schnitzler-tagebuch.acdh.oeaw.ac.at/entry__1915-06-28.html",
 "head":
 "Tagebucheintrag zum 28. Juni 1915",
 "desc":
{"listPerson":
  [
{
 "persName":
 "Stefanie Bachrach",
 "ref":
 "pmb13653"},
 {
 "persName":
 "Edwin Björkman",
 "ref":
 "pmb3283"},
 {
 "persName":
 "Friedrich II. von Preußen",
 "ref":
 "pmb4823"},
 {
 "persName":
 "Ferdinand Kürnberger",
 "ref":
 "pmb19980"},
 {
 "persName":
 "Dora Kallmus",
 "ref":
 "pmb28340"},
 {
 "persName":
 "Ivan Sergeevič Turgenev",
 "ref":
 "pmb26238"}],
 "listBibl":
  [
 {
 "title":
 "Komtesse Mizzi oder: Der Familientag",
 "ref":
 "pmb29931"}
 ,  {
 "title":
 "Der einsame Weg. Schauspiel in fünf Akten",
 "ref":
 "pmb29985"}
 ,  {
 "title":
 "Zwischenspiel. Komödie in drei Akten",
 "ref":
 "pmb29903"}
 ,  {
 "title":
 "Novellen",
 "ref":
 "pmb78123"}
 ,  {
 "title":
 "Die Geschichte von Arthur Pendennis, seine Freuden und Leiden, seine Freunde und sein größter Feind",
 "ref":
 "pmb79720"}
 ,  {
 "title":
 "Punin und Baburin",
 "ref":
 "pmb80038"}
 ],
 "listPlace":
  [
 {
 "placeName":
 "Wien",
 "ref":
 "pmb50"}
 ,  {
 "placeName":
 "Vereinigte Staaten von Amerika [USA]",
 "ref":
 "pmb43406"}
 ]
}
}, {
 "type":
 "wienerschnitzler",
 "color":
 "#6F5106",
 "caption":
 "Wiener Schnitzler",
 "idno":
 "https://wienerschnitzler.org/tag.html#1915-06-28",
 "head":
 "Semmering",
 "desc":
{"listPlace":
  [
 {
 "placeName":
 "Südbahnhotel [Semmering]",
 "ref":
 ""}
 ,  {
 "placeName":
 "Bahnhof Semmering",
 "ref":
 ""}
 ]
}
}, {
 "type":
 "wienerschnitzler",
 "color":
 "#6F5106",
 "caption":
 "Wiener Schnitzler",
 "idno":
 "https://wienerschnitzler.org/tag.html#1915-06-28",
 "head":
 "Wien",
 "desc":
{"listPlace":
  [
 {
 "placeName":
 "X., Favoriten",
 "ref":
 ""}
 ,  {
 "placeName":
 "XVIII., Währing",
 "ref":
 ""}
 ]
}
}] 