[{
 "type":
 "schnitzler-tagebuch",
 "color":
 "#037a33",
 "filename":
 "entry__1916-12-13",
 "caption":
 "Tagebuch",
 "idno":
 "https://schnitzler-tagebuch.acdh.oeaw.ac.at/entry__1916-12-13.html",
 "head":
 "Tagebucheintrag zum 13. Dezember 1916",
 "desc":
{"listPerson":
  [
{
 "persName":
 "Irene Hellmann",
 "ref":
 "pmb18084"},
 {
 "persName":
 "Margarethe Kainz",
 "ref":
 "pmb2273"},
 {
 "persName":
 "Ernest von Koerber",
 "ref":
 "pmb11955"},
 {
 "persName":
 "Julius von Landesberger",
 "ref":
 "pmb12034"},
 {
 "persName":
 "Gertrude Felice von Rheinhardt",
 "ref":
 "pmb27961"},
 {
 "persName":
 "Alexander von Spitzmüller",
 "ref":
 "pmb4642"},
 {
 "persName":
 "Josef II.",
 "ref":
 "pmb3084"},
 {
 "persName":
 "Arthur Kaufmann",
 "ref":
 "pmb2496"}],
 "listBibl":
  [
 {
 "title":
 "Fink und Fliederbusch. Komödie in drei Akten",
 "ref":
 "pmb30881"}
 ]
}
}, {
 "type":
 "wienerschnitzler",
 "color":
 "#6F5106",
 "caption":
 "Wiener Schnitzler",
 "idno":
 "https://wienerschnitzler.org/tag.html#1916-12-13",
 "head":
 "Wien",
 "desc":
{"listPlace":
  [
 {
 "placeName":
 "I., Innere Stadt",
 "ref":
 ""}
 ,  {
 "placeName":
 "XVIII., Währing",
 "ref":
 ""}
 ]
}
}, {
 "type":
 "kalliope-verbund",
 "color":
 "#003574",
 "caption":
 "Kalliope Verbundkatalog",
 "idno":
 "http://kalliope-verbund.info/DE-2498-HS00044766",
 "head":
 "Schnitzler, Arthur an Blum, ... [Briefe]",
 "text":
 "1 Bl.Durchschl."
}] 