[{
 "type":
 "schnitzler-tagebuch",
 "color":
 "#037a33",
 "filename":
 "entry__1920-11-14",
 "caption":
 "Tagebuch",
 "idno":
 "https://schnitzler-tagebuch.acdh.oeaw.ac.at/entry__1920-11-14.html",
 "head":
 "Tagebucheintrag zum 14. November 1920",
 "desc":
{"listPerson":
  [
{
 "persName":
 "Eugenie Bachrach",
 "ref":
 "pmb13644"},
 {
 "persName":
 "Gabriel Beer-Hofmann",
 "ref":
 "pmb13923"},
 {
 "persName":
 "Gertrud Hammerschlag",
 "ref":
 "pmb17803"},
 {
 "persName":
 "Marianne Rie",
 "ref":
 "pmb23376"},
 {
 "persName":
 "Josefine Schipper",
 "ref":
 "pmb24194"},
 {
 "persName":
 "Siegfried Trebitsch",
 "ref":
 "pmb12968"},
 {
 "persName":
 "Mirjam Beer-Hofmann",
 "ref":
 "pmb2668"},
 {
 "persName":
 "Naëmah Beer-Hofmann",
 "ref":
 "pmb2534"},
 {
 "persName":
 "Victor Zuckerkandl",
 "ref":
 "pmb54787"}],
 "listBibl":
  [
 {
 "title":
 "Der Gang zum Weiher. Dramatische Dichtung",
 "ref":
 "pmb30775"}
 ],
 "listPlace":
  [
 {
 "placeName":
 "Pokornygasse",
 "ref":
 "pmb92452"}
 ,  {
 "placeName":
 "Děčín",
 "ref":
 "pmb90372"}
 ]
}
}] 