[{
 "type":
 "schnitzler-tagebuch",
 "color":
 "#037a33",
 "filename":
 "entry__1920-06-23",
 "caption":
 "Tagebuch",
 "idno":
 "https://schnitzler-tagebuch.acdh.oeaw.ac.at/entry__1920-06-23.html",
 "head":
 "Tagebucheintrag zum 23. Juni 1920",
 "desc":
{"listPerson":
  [
{
 "persName":
 "Lili Cappellini",
 "ref":
 "pmb2238"},
 {
 "persName":
 "Leopoldine Wertheimer",
 "ref":
 "pmb26990"},
 {
 "persName":
 "Margarethe Wertheimer",
 "ref":
 "pmb26993"},
 {
 "persName":
 "Wilhelm Wertheimer",
 "ref":
 "pmb26997"},
 {
 "persName":
 "Irma Hoffmeister",
 "ref":
 "pmb18391"}],
 "listBibl":
  [
 {
 "title":
 "Der Gang zum Weiher. Dramatische Dichtung",
 "ref":
 "pmb30775"}
 ,  {
 "title":
 "Die Versäumten",
 "ref":
 "pmb33802"}
 ],
 "listPlace":
  [
 {
 "placeName":
 "Kletschka-Höhe",
 "ref":
 "pmb92336"}
 ]
}
}] 