[{
 "type":
 "schnitzler-tagebuch",
 "color":
 "#037a33",
 "filename":
 "entry__1920-02-03",
 "caption":
 "Tagebuch",
 "idno":
 "https://schnitzler-tagebuch.acdh.oeaw.ac.at/entry__1920-02-03.html",
 "head":
 "Tagebucheintrag zum 3. Februar 1920",
 "desc":
{"listPerson":
  [
{
 "persName":
 "Gustav Schwarzkopf",
 "ref":
 "pmb12740"},
 {
 "persName":
 "Frieda Pollak",
 "ref":
 "pmb22728"},
 {
 "persName":
 "Olga Schnitzler",
 "ref":
 "pmb2173"},
 {
 "persName":
 "Wagner",
 "ref":
 "pmb26566"}]
}
}, {
 "type":
 "wienerschnitzler",
 "color":
 "#6F5106",
 "caption":
 "Wiener Schnitzler",
 "idno":
 "https://wienerschnitzler.org/tag.html#1920-02-03",
 "head":
 "Wien",
 "desc":
{"listPlace":
  [
 {
 "placeName":
 "I., Innere Stadt",
 "ref":
 ""}
 ,  {
 "placeName":
 "IX., Alsergrund",
 "ref":
 ""}
 ,  {
 "placeName":
 "XVIII., Währing",
 "ref":
 ""}
 ]
}
}] 