[{
 "type":
 "schnitzler-tagebuch",
 "color":
 "#037a33",
 "filename":
 "entry__1922-11-03",
 "caption":
 "Tagebuch",
 "idno":
 "https://schnitzler-tagebuch.acdh.oeaw.ac.at/entry__1922-11-03.html",
 "head":
 "Tagebucheintrag zum 3. November 1922",
 "desc":
{"listPerson":
  [
{
 "persName":
 "Joachim Gasquet",
 "ref":
 "pmb7350"},
 {
 "persName":
 "Hedy Kempny",
 "ref":
 "pmb19262"},
 {
 "persName":
 "Heinrich Schnitzler",
 "ref":
 "pmb12692"},
 {
 "persName":
 "Louise Schnitzler",
 "ref":
 "pmb12701"},
 {
 "persName":
 "Else Lederer",
 "ref":
 "pmb25175"},
 {
 "persName":
 "Rudolf Wantoch",
 "ref":
 "pmb26672"},
 {
 "persName":
 "Max Leitner",
 "ref":
 "pmb20270"}],
 "listBibl":
  [
 {
 "title":
 "Weihnachts-Einkäufe",
 "ref":
 "pmb30163"}
 ,  {
 "title":
 "Liebelei. Schauspiel in drei Akten",
 "ref":
 "pmb29917"}
 ,  {
 "title":
 "",
 "ref":
 "pmb29951"}
 ,  {
 "title":
 "Reigen. Zehn Dialoge",
 "ref":
 "pmb29855"}
 ,  {
 "title":
 "Die letzten Masken",
 "ref":
 "pmb29877"}
 ,  {
 "title":
 "Il y a une volupté dans la douleur",
 "ref":
 "pmb79338"}
 ],
 "listPlace":
  [
 {
 "placeName":
 "Burgring",
 "ref":
 "pmb274"}
 ,  {
 "placeName":
 "Teplice",
 "ref":
 "pmb955"}
 ,  {
 "placeName":
 "Leipzig",
 "ref":
 "pmb864"}
 ,  {
 "placeName":
 "Europa",
 "ref":
 "pmb468"}
 ]
}
}, {
 "type":
 "URL",
 "subtype":
 "schnitzler-kultur",
 "filename":
 "pmb62703",
 "idno":
 "https://schnitzler-kultur.acdh.oeaw.ac.at/pmb62703.html",
 "head":
 "Lesung von Die letzten Masken, Weihnachts-Einkäufe, Zum großen Wurstl, abgebrochen, 3.11.1922",
 "desc":
{"listBibl":
  [
 {
 "title":
 "Die letzten Masken",
 "ref":
 ""}
 ,  {
 "title":
 "Weihnachts-Einkäufe",
 "ref":
 ""}
 ,  {
 "title":
 "Zum großen Wurstel. Burleske in einem Akt",
 "ref":
 ""}
 ],
 "listPerson":
  [
{
 "persName":
 "Arthur Schnitzler",
 "ref":
 ""},
 {
 "persName":
 "Rudolf Wantoch",
 "ref":
 ""}],
 "listPlace":
  [
 {
 "placeName":
 "Lipový dvůr",
 "ref":
 ""}
 ]
}
}, {
 "type":
 "schnitzler-traeume",
 "subtype":
 "#ISBN978-3-8353-1029-2",
 "color":
 "#1193CC",
 "caption":
 "Traumtagebuch",
 "head":
 "Traum vom 3. November 1922",
 "source":
 "Arthur Schnitzler: Träume. Das Traumtagebuch 1875–1931. Herausgegeben von Peter Michael Braunwarth und Leo A. Lensing. Göttingen: Wallstein 2012 (Bibliothek Janowitz, Bd. 20)"
}] 