[{
 "type":
 "Arthur-Schnitzler-digital",
 "color":
 "#801e23",
 "caption":
 "Arthur Schnitzler digital (Werke 1905–1931)",
 "idno":
 "https://www.schnitzler-edition.net",
 "head":
 "Die Frau des Richters, Typoskript",
 "text":
 "Publikation in Vorbereitung"
}, {
 "type":
 "schnitzler-tagebuch",
 "color":
 "#037a33",
 "filename":
 "entry__1922-11-23",
 "caption":
 "Tagebuch",
 "idno":
 "https://schnitzler-tagebuch.acdh.oeaw.ac.at/entry__1922-11-23.html",
 "head":
 "Tagebucheintrag zum 23. November 1922",
 "desc":
{"listPerson":
  [
{
 "persName":
 "Joseph Gregor",
 "ref":
 "pmb7525"},
 {
 "persName":
 "Markus Hajek",
 "ref":
 "pmb2284"},
 {
 "persName":
 "Hedwig Keller",
 "ref":
 "pmb19250"},
 {
 "persName":
 "Hedy Kempny",
 "ref":
 "pmb19262"},
 {
 "persName":
 "Walter Pfund",
 "ref":
 "pmb22499"}],
 "listBibl":
  [
 {
 "title":
 "Tagebuch",
 "ref":
 "pmb33243"}
 ]
}
}] 