[{
 "type":
 "schnitzler-tagebuch",
 "color":
 "#037a33",
 "filename":
 "entry__1922-05-03",
 "caption":
 "Tagebuch",
 "idno":
 "https://schnitzler-tagebuch.acdh.oeaw.ac.at/entry__1922-05-03.html",
 "head":
 "Tagebucheintrag zum 3. Mai 1922",
 "desc":
{"listPerson":
  [
{
 "persName":
 "Bertha Brevée",
 "ref":
 "pmb14543"},
 {
 "persName":
 "Vincent van Gogh",
 "ref":
 "pmb11464"},
 {
 "persName":
 "Bart Antonij van der Leck",
 "ref":
 "pmb20209"},
 {
 "persName":
 "Eliza Johannes de Meester",
 "ref":
 "pmb21269"},
 {
 "persName":
 "Elly Reicher",
 "ref":
 "pmb23178"},
 {
 "persName":
 "Emanuel Reicher",
 "ref":
 "pmb12491"},
 {
 "persName":
 "Eduard Rutger Verkade",
 "ref":
 "pmb28839"},
 {
 "persName":
 "Hendrik Pieter Bremmer",
 "ref":
 "pmb14516"},
 {
 "persName":
 "Cornelius Petrus van Rossem",
 "ref":
 "pmb23615"},
 {
 "persName":
 "Anton G. Kröller",
 "ref":
 "pmb19786"},
 {
 "persName":
 "Hellmuth von Lucius von Stoedten",
 "ref":
 "pmb20644"},
 {
 "persName":
 "Lodewijk Emanuel Tels",
 "ref":
 "pmb25918"}],
 "listPlace":
  [
 {
 "placeName":
 "Den Haag",
 "ref":
 "pmb58810"}
 ]
}
}, {
 "type":
 "wienerschnitzler",
 "color":
 "#6F5106",
 "caption":
 "Wiener Schnitzler",
 "idno":
 "https://wienerschnitzler.org/tag.html#1922-05-03",
 "head":
 "Den Haag",
 "desc":
{"listPlace":
  [
 {
 "placeName":
 "Bezuidenhoutseweg 65",
 "ref":
 ""}
 ,  {
 "placeName":
 "Museum Kröller",
 "ref":
 ""}
 ]
}
}, {
 "type":
 "URL",
 "subtype":
 "schnitzler-kultur",
 "filename":
 "pmb298218",
 "idno":
 "https://schnitzler-kultur.acdh.oeaw.ac.at/pmb298218.html",
 "head":
 "Besuch des Museums Kröller, 3.5.1922",
 "desc":
{"listPerson":
  [
{
 "persName":
 "Arthur Schnitzler",
 "ref":
 ""}],
 "listPlace":
  [
 {
 "placeName":
 "Museum Kröller",
 "ref":
 ""}
 ]
}
}] 