[{
 "type":
 "Arthur-Schnitzler-digital",
 "color":
 "#801e23",
 "caption":
 "Arthur Schnitzler digital (Werke 1905–1931)",
 "idno":
 "https://www.schnitzler-edition.net",
 "head":
 "Die Frau des Richters, Typoskript",
 "text":
 "Publikation in Vorbereitung"
}, {
 "type":
 "schnitzler-tagebuch",
 "color":
 "#037a33",
 "filename":
 "entry__1923-03-22",
 "caption":
 "Tagebuch",
 "idno":
 "https://schnitzler-tagebuch.acdh.oeaw.ac.at/entry__1923-03-22.html",
 "head":
 "Tagebucheintrag zum 22. März 1923",
 "desc":
{"listPerson":
  [
{
 "persName":
 "Lili Cappellini",
 "ref":
 "pmb2238"},
 {
 "persName":
 "Hedy Kempny",
 "ref":
 "pmb19262"},
 {
 "persName":
 "Robert Lichtenstern",
 "ref":
 "pmb20398"},
 {
 "persName":
 "Vilma Lichtenstern",
 "ref":
 "pmb20400"},
 {
 "persName":
 "Hans Liebstöckl",
 "ref":
 "pmb20424"},
 {
 "persName":
 "Josef Karl Ratislav",
 "ref":
 "pmb23079"},
 {
 "persName":
 "Heinrich Schnitzler",
 "ref":
 "pmb12692"},
 {
 "persName":
 "Gustav Schwarzkopf",
 "ref":
 "pmb12740"},
 {
 "persName":
 "Wilhelm Speyer",
 "ref":
 "pmb3873"},
 {
 "persName":
 "Elisabeth Steinrück",
 "ref":
 "pmb25427"},
 {
 "persName":
 "Otto Tressler",
 "ref":
 "pmb12971"},
 {
 "persName":
 "Frank Wedekind",
 "ref":
 "pmb13068"},
 {
 "persName":
 "Albert Steinrück",
 "ref":
 "pmb12837"},
 {
 "persName":
 "Olga Schnitzler",
 "ref":
 "pmb2173"}],
 "listBibl":
  [
 {
 "title":
 "Fräulein Else",
 "ref":
 "pmb29941"}
 ,  {
 "title":
 "Die Frau des Richters. Novelle",
 "ref":
 "pmb30751"}
 ,  {
 "title":
 "Die Schwestern oder Casanova in Spa. Lustspiel in Versen",
 "ref":
 "pmb30819"}
 ,  {
 "title":
 "Traumnovelle",
 "ref":
 "pmb30851"}
 ,  {
 "title":
 "Schwermut der Jahreszeiten",
 "ref":
 "pmb78416"}
 ,  {
 "title":
 "Der Marquis von Keith. Schauspiel in 5 Aufzügen",
 "ref":
 "pmb76462"}
 ],
 "listPlace":
  [
 {
 "placeName":
 "Burgtheater",
 "ref":
 "pmb14"}
 ]
}
}, {
 "type":
 "URL",
 "subtype":
 "schnitzler-kultur",
 "filename":
 "pmb210224",
 "idno":
 "https://schnitzler-kultur.acdh.oeaw.ac.at/pmb210224.html",
 "head":
 "Aufführung von Der Marquis von Keith, 22.3.1923",
 "desc":
{"listBibl":
  [
 {
 "title":
 "Der Marquis von Keith. Schauspiel in 5 Aufzügen",
 "ref":
 ""}
 ],
 "listPerson":
  [
{
 "persName":
 "Albert Steinrück",
 "ref":
 ""},
 {
 "persName":
 "Arthur Schnitzler",
 "ref":
 ""}],
 "listPlace":
  [
 {
 "placeName":
 "Renaissancetheater",
 "ref":
 ""}
 ]
}
}, {
 "type":
 "schnitzler-cmif",
 "subtype":
 "#m5ca120f-450d-4a59-9a44-d5822a34aee9",
 "color":
 "#654321",
 "caption":
 "Gedruckte Briefwechsel",
 "head":
 "Arthur Schnitzler an Gustaf Linden, 22.3.1923",
 "source":
 "Arthur Schnitzler, Gustaf Linden: Ein Briefwechsel. 1907–1929, Wien: Edition Praesens 2005 (Wechselbeziehungen Österreich-Norden, Band 7)."
}] 