[{
 "type":
 "schnitzler-tagebuch",
 "color":
 "#037a33",
 "filename":
 "entry__1926-03-28",
 "caption":
 "Tagebuch",
 "idno":
 "https://schnitzler-tagebuch.acdh.oeaw.ac.at/entry__1926-03-28.html",
 "head":
 "Tagebucheintrag zum 28. März 1926",
 "desc":
{"listPerson":
  [
{
 "persName":
 "Rudolf Askonas",
 "ref":
 "pmb13541"},
 {
 "persName":
 "Melitta Eger",
 "ref":
 "pmb15676"},
 {
 "persName":
 "Hedy Kempny",
 "ref":
 "pmb19262"},
 {
 "persName":
 "Karl Pollak",
 "ref":
 "pmb22740"},
 {
 "persName":
 "Josef II.",
 "ref":
 "pmb3084"}],
 "listBibl":
  [
 {
 "title":
 "Aphoristisches",
 "ref":
 "pmb35745"}
 ],
 "listPlace":
  [
 {
 "placeName":
 "Satzberg",
 "ref":
 "pmb91663"}
 ,  {
 "placeName":
 "",
 "ref":
 "pmb90533"}
 ]
}
}] 