[{
 "type":
 "schnitzler-tagebuch",
 "color":
 "#037a33",
 "filename":
 "entry__1927-02-27",
 "caption":
 "Tagebuch",
 "idno":
 "https://schnitzler-tagebuch.acdh.oeaw.ac.at/entry__1927-02-27.html",
 "head":
 "Tagebucheintrag zum 27. Februar 1927",
 "desc":
{"listPerson":
  [
{
 "persName":
 "Lili Cappellini",
 "ref":
 "pmb2238"},
 {
 "persName":
 "Vilma Lichtenstern",
 "ref":
 "pmb20400"},
 {
 "persName":
 "Philipp Menczel",
 "ref":
 "pmb3119"},
 {
 "persName":
 "Clara Katharina Pollaczek",
 "ref":
 "pmb12435"},
 {
 "persName":
 "Olga Schnitzler",
 "ref":
 "pmb2173"},
 {
 "persName":
 "Leo Sirota",
 "ref":
 "pmb9910"}],
 "listBibl":
  [
 {
 "title":
 "Zug der Schatten",
 "ref":
 "pmb32049"}
 ],
 "listPlace":
  [
 {
 "placeName":
 "Wien",
 "ref":
 "pmb50"}
 ]
}
}, {
 "type":
 "schnitzler-mikrofilme-daten",
 "color":
 "#6e7b8b",
 "filename":
 "1428139_0024",
 "caption":
 "Mikroverfilmung des Nachlasses",
 "idno":
 "https://schnitzler-mikrofilme.acdh.oeaw.ac.at/1428139_0024.html",
 "head":
 "Mappe A52",
 "text":
 "Abschrift eines Briefs zu Das Diagramm"
}] 