[{
 "type":
 "schnitzler-tagebuch",
 "color":
 "#037a33",
 "filename":
 "entry__1927-07-05",
 "caption":
 "Tagebuch",
 "idno":
 "https://schnitzler-tagebuch.acdh.oeaw.ac.at/entry__1927-07-05.html",
 "head":
 "Tagebucheintrag zum 5. Juli 1927",
 "desc":
{"listPerson":
  [
{
 "persName":
 "Jean Billiter",
 "ref":
 "pmb10931"},
 {
 "persName":
 "Lili Cappellini",
 "ref":
 "pmb2238"},
 {
 "persName":
 "Hedwig Sophie Verena Gossman",
 "ref":
 "pmb17258"},
 {
 "persName":
 "Clara Katharina Pollaczek",
 "ref":
 "pmb12435"},
 {
 "persName":
 "Heinrich Schnitzler",
 "ref":
 "pmb12692"},
 {
 "persName":
 "Gustav Heinrich von Gans-Putlitz",
 "ref":
 "pmb16906"},
 {
 "persName":
 "Franz Horch",
 "ref":
 "pmb11774"},
 {
 "persName":
 "Edith Schneider",
 "ref":
 "pmb24375"},
 {
 "persName":
 "Norbert Hoffmann",
 "ref":
 "pmb4401"},
 {
 "persName":
 "Frieda Pollak",
 "ref":
 "pmb22728"},
 {
 "persName":
 "Olga Schnitzler",
 "ref":
 "pmb2173"}],
 "listBibl":
  [
 {
 "title":
 "Der Geist im Wort und der Geist in der Tat",
 "ref":
 "pmb30051"}
 ,  {
 "title":
 "Carl Immermann",
 "ref":
 "pmb80569"}
 ],
 "listPlace":
  [
 {
 "placeName":
 "London",
 "ref":
 "pmb224"}
 ,  {
 "placeName":
 "Venedig",
 "ref":
 "pmb462"}
 ,  {
 "placeName":
 "Florenz",
 "ref":
 "pmb263"}
 ]
}
}] 