[{
 "type":
 "schnitzler-tagebuch",
 "color":
 "#037a33",
 "filename":
 "entry__1928-10-12",
 "caption":
 "Tagebuch",
 "idno":
 "https://schnitzler-tagebuch.acdh.oeaw.ac.at/entry__1928-10-12.html",
 "head":
 "Tagebucheintrag zum 12. Oktober 1928",
 "desc":
{"listPerson":
  [
{
 "persName":
 "Julia Bertha Culp",
 "ref":
 "pmb11123"},
 {
 "persName":
 "Walther Friedmann",
 "ref":
 "pmb16675"},
 {
 "persName":
 "Wilhelm Ginzkey",
 "ref":
 "pmb17035"},
 {
 "persName":
 "Paul Kohner",
 "ref":
 "pmb19515"},
 {
 "persName":
 "Mary I. Philbin",
 "ref":
 "pmb22504"},
 {
 "persName":
 "Heinrich Schnitzler",
 "ref":
 "pmb12692"},
 {
 "persName":
 "Johann Strauss",
 "ref":
 "pmb12867"},
 {
 "persName":
 "Erwin Piscator",
 "ref":
 "pmb9284"},
 {
 "persName":
 "Olga Schnitzler",
 "ref":
 "pmb2173"}],
 "listBibl":
  [
 {
 "title":
 "Spiel im Morgengrauen. Novelle",
 "ref":
 "pmb32131"}
 ,  {
 "title":
 "Merry-Go-Round",
 "ref":
 "pmb80760"}
 ,  {
 "title":
 "Casanova",
 "ref":
 "pmb77667"}
 ],
 "listPlace":
  [
 {
 "placeName":
 "Berlin",
 "ref":
 "pmb168"}
 ]
}
}, {
 "type":
 "URL",
 "subtype":
 "schnitzler-kultur",
 "filename":
 "pmb233619",
 "idno":
 "https://schnitzler-kultur.acdh.oeaw.ac.at/pmb233619.html",
 "head":
 "Aufführung von Casanova, 12.10.1928",
 "desc":
{"listOrg":
  [
 {
 "orgName":
 "Großes Schauspielhaus",
 "ref":
 ""}
 ],
 "listBibl":
  [
 {
 "title":
 "Casanova",
 "ref":
 ""}
 ],
 "listPerson":
  [
{
 "persName":
 "Arthur Schnitzler",
 "ref":
 ""}],
 "listPlace":
  [
 {
 "placeName":
 "Großes Schauspielhaus",
 "ref":
 ""}
 ]
}
}, {
 "type":
 "pollaczek",
 "color":
 "#1e81b0",
 "filename":
 "ckp605",
 "caption":
 "Pollaczek: Schnitzler und ich",
 "idno":
 "https://pollaczek.acdh.oeaw.ac.at/ckp605.html",
 "head":
 "Arthur Schnitzler an Clara Katharina Pollaczek, 12. Oktober 1928"
}, {
 "type":
 "kalliope-verbund",
 "color":
 "#003574",
 "caption":
 "Kalliope Verbundkatalog",
 "idno":
 "http://kalliope-verbund.info/DE-2498-HS00078938",
 "head":
 "Hoffmann, Norbert an Schnitzler, Arthur [Briefe]",
 "text":
 "1 Bl.Durchschl.",
 "desc":
{"listPerson":
  [
{
 "persName":
 "Norbert (1891-1977) Hoffmann",
 "ref":
 "http://d-nb.info/gnd/1113760052"}]
}
}] 