[{
 "type":
 "schnitzler-tagebuch",
 "color":
 "#037a33",
 "filename":
 "entry__1930-07-17",
 "caption":
 "Tagebuch",
 "idno":
 "https://schnitzler-tagebuch.acdh.oeaw.ac.at/entry__1930-07-17.html",
 "head":
 "Tagebucheintrag zum 17. Juli 1930",
 "desc":
{"listPerson":
  [
{
 "persName":
 "Lili Cappellini",
 "ref":
 "pmb2238"},
 {
 "persName":
 "Suzanne Clauser",
 "ref":
 "pmb15015"},
 {
 "persName":
 "Dora Michaelis",
 "ref":
 "pmb2774"},
 {
 "persName":
 "Clara Katharina Pollaczek",
 "ref":
 "pmb12435"},
 {
 "persName":
 "Erich Maria Remarque",
 "ref":
 "pmb9480"},
 {
 "persName":
 "Heinrich Schnitzler",
 "ref":
 "pmb12692"},
 {
 "persName":
 "Gustav Schwarzkopf",
 "ref":
 "pmb12740"},
 {
 "persName":
 "Ruth Schnitzler",
 "ref":
 "pmb5960"},
 {
 "persName":
 "Julien Green",
 "ref":
 "pmb17345"}],
 "listBibl":
  [
 {
 "title":
 "Adrienne Mesurat",
 "ref":
 "pmb80623"}
 ],
 "listPlace":
  [
 {
 "placeName":
 "Buchs",
 "ref":
 "pmb859"}
 ,  {
 "placeName":
 "Chur",
 "ref":
 "pmb2448"}
 ,  {
 "placeName":
 "St. Moritz",
 "ref":
 "pmb44374"}
 ,  {
 "placeName":
 "Thalheim bei Wels",
 "ref":
 "pmb91887"}
 ]
}
}, {
 "type":
 "wienerschnitzler",
 "color":
 "#6F5106",
 "caption":
 "Wiener Schnitzler",
 "idno":
 "https://wienerschnitzler.org/tag.html#1930-07-17",
 "head":
 "Buchs",
 "desc":
{"listPlace":
  [
 {
 "placeName":
 "Bahnhof Buchs SG",
 "ref":
 ""}
 ]
}
}, {
 "type":
 "wienerschnitzler",
 "color":
 "#6F5106",
 "caption":
 "Wiener Schnitzler",
 "idno":
 "https://wienerschnitzler.org/tag.html#1930-07-17",
 "head":
 "Chur",
 "desc":
{"listPlace":
  [
 {
 "placeName":
 "Bahnhof Chur",
 "ref":
 ""}
 ]
}
}, {
 "type":
 "wienerschnitzler",
 "color":
 "#6F5106",
 "caption":
 "Wiener Schnitzler",
 "idno":
 "https://wienerschnitzler.org/tag.html#1930-07-17",
 "head":
 "St. Moritz",
 "desc":
{"listPlace":
  [
 {
 "placeName":
 "Grand Hotel Victoria",
 "ref":
 ""}
 ]
}
}, {
 "type":
 "pollaczek",
 "color":
 "#1e81b0",
 "filename":
 "ckp800",
 "caption":
 "Pollaczek: Schnitzler und ich",
 "idno":
 "https://pollaczek.acdh.oeaw.ac.at/ckp800.html",
 "head":
 "Tagebuch von Clara Katharina Pollaczek, 15.–20. Juli 1930"
}, {
 "type":
 "schnitzler-cmif",
 "subtype":
 "#n0827e77-245d-4359-a0b0-5b601a5370ee",
 "color":
 "#654321",
 "caption":
 "Gedruckte Briefwechsel",
 "head":
 "Arthur Schnitzler an Hedy Kempny, 17.7.1930",
 "source":
 "Hedy Kempny und Arthur Schnitzler: Das Mädchen mit den dreizehn Seelen. Eine Korrespondenz ergänzt durch Blätter aus Hedy Kempnys Tagebuch sowie durch eine Auswahl ihrer Erzählungen. Hg. v. Heinz P. Adamek. Reinbek bei Hamburg: Rowohlt 1984. (Neue Frau)"
}, {
 "type":
 "schnitzler-traeume",
 "subtype":
 "#ISBN978-3-8353-1029-2",
 "color":
 "#1193CC",
 "caption":
 "Traumtagebuch",
 "head":
 "Traum vom 17. Juli 1930",
 "source":
 "Arthur Schnitzler: Träume. Das Traumtagebuch 1875–1931. Herausgegeben von Peter Michael Braunwarth und Leo A. Lensing. Göttingen: Wallstein 2012 (Bibliothek Janowitz, Bd. 20)"
}] 